setup.py
PyGlobe.egg-info/PKG-INFO
PyGlobe.egg-info/SOURCES.txt
PyGlobe.egg-info/dependency_links.txt
PyGlobe.egg-info/requires.txt
PyGlobe.egg-info/top_level.txt
pyglobe/__init__.py
pyglobe/core.py
pyglobe/exceptions.py